SklearnXuexiShouceChuyiFix1/README.md
SklearnXuexiShouceChuyiFix1/__init__.py
SklearnXuexiShouceChuyiFix1/__main__.py
SklearnXuexiShouceChuyiFix1/file.epub
SklearnXuexiShouceChuyiFix1/index.html
SklearnXuexiShouceChuyiFix1/css/__init__.py
SklearnXuexiShouceChuyiFix1/css/annotations.css
SklearnXuexiShouceChuyiFix1/css/main.css
SklearnXuexiShouceChuyiFix1/css/normalize.css
SklearnXuexiShouceChuyiFix1/css/popup.css
SklearnXuexiShouceChuyiFix1/font/__init__.py
SklearnXuexiShouceChuyiFix1/font/fontello.eot
SklearnXuexiShouceChuyiFix1/font/fontello.svg
SklearnXuexiShouceChuyiFix1/font/fontello.ttf
SklearnXuexiShouceChuyiFix1/font/fontello.woff
SklearnXuexiShouceChuyiFix1/img/__init__.py
SklearnXuexiShouceChuyiFix1/img/annotator-glyph-sprite.png
SklearnXuexiShouceChuyiFix1/img/annotator-icon-sprite.png
SklearnXuexiShouceChuyiFix1/img/apple-touch-icon.png
SklearnXuexiShouceChuyiFix1/img/cancelfullscreen.png
SklearnXuexiShouceChuyiFix1/img/close.png
SklearnXuexiShouceChuyiFix1/img/fullscreen.png
SklearnXuexiShouceChuyiFix1/img/loader.gif
SklearnXuexiShouceChuyiFix1/img/menu-icon.png
SklearnXuexiShouceChuyiFix1/img/save.png
SklearnXuexiShouceChuyiFix1/img/saved.png
SklearnXuexiShouceChuyiFix1/img/settings-s.png
SklearnXuexiShouceChuyiFix1/img/settings.png
SklearnXuexiShouceChuyiFix1/img/star.png
SklearnXuexiShouceChuyiFix1/js/__init__.py
SklearnXuexiShouceChuyiFix1/js/epub.js
SklearnXuexiShouceChuyiFix1/js/epub.min.js
SklearnXuexiShouceChuyiFix1/js/epub.min.map
SklearnXuexiShouceChuyiFix1/js/hooks.min.js
SklearnXuexiShouceChuyiFix1/js/hooks.min.map
SklearnXuexiShouceChuyiFix1/js/reader.js
SklearnXuexiShouceChuyiFix1/js/reader.js.map
SklearnXuexiShouceChuyiFix1/js/reader.min.js
SklearnXuexiShouceChuyiFix1/js/reader.min.map
SklearnXuexiShouceChuyiFix1/js/hooks/__init__.py
SklearnXuexiShouceChuyiFix1/js/hooks/extensions/__init__.py
SklearnXuexiShouceChuyiFix1/js/hooks/extensions/highlight.js
SklearnXuexiShouceChuyiFix1/js/libs/__init__.py
sklearn_xuexi_shouce_chuyi_fix1-2025.3.24.0.dist-info/METADATA
sklearn_xuexi_shouce_chuyi_fix1-2025.3.24.0.dist-info/WHEEL
sklearn_xuexi_shouce_chuyi_fix1-2025.3.24.0.dist-info/entry_points.txt
sklearn_xuexi_shouce_chuyi_fix1-2025.3.24.0.dist-info/top_level.txt
sklearn_xuexi_shouce_chuyi_fix1-2025.3.24.0.dist-info/RECORD
